pyexch/__main__.py
pyexch/exchange.py
pyexch/keystore.py
pyexch/pyexch.py
pyexch-0.0.2.dist-info/LICENSE
pyexch-0.0.2.dist-info/METADATA
pyexch-0.0.2.dist-info/WHEEL
pyexch-0.0.2.dist-info/entry_points.txt
pyexch-0.0.2.dist-info/top_level.txt
pyexch-0.0.2.dist-info/RECORD
