Metadata-Version: 2.1
Name: pyexch
Version: 0.0.2
Summary: Python CLI Exchange Rest Client
Home-page: https://github.com/brianddk/pyexch
Author: brianddk
Author-email: brianddk@users.noreply.github.com
License: Apache-2.0
Requires-Python: >=3.8.2
License-File: LICENSE
Requires-Dist: coinbase >=2.1.0
Requires-Dist: coinbase-advanced-py >=1.2.0
Requires-Dist: trezor >=0.13.8
Requires-Dist: pyjson5 >=1.6.6
